kaiju_models/__init__.py
kaiju_models/bases.py
kaiju_models/fields.py
kaiju_models-1.0.5.dist-info/licenses/LICENSE
kaiju_models-1.0.5.dist-info/METADATA
kaiju_models-1.0.5.dist-info/WHEEL
kaiju_models-1.0.5.dist-info/top_level.txt
kaiju_models-1.0.5.dist-info/RECORD
