Metadata-Version: 2.4
Name: kaiju-models
Version: 1.0.5
Summary: Base classes and services for a backend application
Author-email: Taraskin Anton <antonnidhoggr@me.com>
Maintainer-email: Taraskin Anton <antonnidhoggr@me.com>
Project-URL: Homepage, https://gitlab.com/kaiju-python/kaiju-models
Project-URL: Documentation, https://kaiju-models.readthedocs.io
Keywords: kaiju
Classifier: Development Status :: 4 - Beta
Classifier: Programming Language :: Python :: 3
Classifier: Programming Language :: Python :: 3 :: Only
Classifier: Programming Language :: Python :: Implementation :: CPython
Requires-Python: >=3.11
License-File: LICENSE
Requires-Dist: msgspec
Provides-Extra: dev
Requires-Dist: uv; extra == "dev"
Requires-Dist: pre-commit; extra == "dev"
Requires-Dist: bump-my-version; extra == "dev"
Requires-Dist: black; extra == "dev"
Requires-Dist: isort; extra == "dev"
Requires-Dist: bandit; extra == "dev"
Requires-Dist: pyupgrade; extra == "dev"
Requires-Dist: pyroma; extra == "dev"
Requires-Dist: pylint; extra == "dev"
Requires-Dist: pytest; extra == "dev"
Requires-Dist: pytest-asyncio; extra == "dev"
Requires-Dist: pytest-aiohttp; extra == "dev"
Requires-Dist: docker; extra == "dev"
Requires-Dist: coverage; extra == "dev"
Provides-Extra: docs
Requires-Dist: sphinx; extra == "docs"
Requires-Dist: python-docs-theme; extra == "docs"
Dynamic: license-file
